asyncgelf/__init__.py
asyncgelf/asyncgelf.py
asyncgelf-1.2.0.dist-info/LICENSE
asyncgelf-1.2.0.dist-info/METADATA
asyncgelf-1.2.0.dist-info/WHEEL
asyncgelf-1.2.0.dist-info/top_level.txt
asyncgelf-1.2.0.dist-info/RECORD
