Metadata-Version: 2.1
Name: asyncgelf
Version: 1.2.0
Summary: Async python logging handlers that send messages in the Graylog Extended Log Format (GELF).
Home-page: https://github.com/malinkinsa/asyncgelf
Download-URL: https://github.com/malinkinsa/asyncgelf/archive/refs/tags/1.2.0.tar.gz
Author: Sergey Malinkin
Author-email: malinkinsa@yandex.ru
License: MIT
Keywords: gelf logging graylog graylog2 tcp udp http
Classifier: Development Status :: 5 - Production/Stable
Classifier: Intended Audience :: Developers
Classifier: License :: OSI Approved :: MIT License
Classifier: Operating System :: OS Independent
Classifier: Programming Language :: Python :: 3.7
Classifier: Programming Language :: Python :: 3.8
Classifier: Programming Language :: Python :: 3.9
Classifier: Programming Language :: Python :: 3.10
Classifier: Programming Language :: Python :: 3.11
Classifier: Programming Language :: Python :: 3.12
Classifier: Topic :: Software Development :: Libraries :: Python Modules
Classifier: Topic :: System :: Logging
License-File: LICENSE
Requires-Dist: asyncio
Requires-Dist: httpx
